{"nodes": [{"id": "tasks_overhaul_plan_local_first_storage", "label": "Local-first conversation storage", "file_type": "rationale", "source_file": "tasks/overhaul-plan.md", "source_location": null, "source_url": null, "captured_at": null, "author": null, "contributor": null}, {"id": "tasks_overhaul_plan_client_owned_history", "label": "Client-owned history (no X-Hermes-Session-Id)", "file_type": "rationale", "source_file": "tasks/overhaul-plan.md", "source_location": null, "source_url": null, "captured_at": null, "author": null, "contributor": null}, {"id": "tasks_overhaul_plan_pure_logic_in_kit", "label": "Pure logic in HermesVoiceKit", "file_type": "rationale", "source_file": "tasks/overhaul-plan.md", "source_location": null, "source_url": null, "captured_at": null, "author": null, "contributor": null}, {"id": "tasks_overhaul_plan_flock_single_instance", "label": "flock single-instance enforcement", "file_type": "rationale", "source_file": "tasks/overhaul-plan.md", "source_location": null, "source_url": null, "captured_at": null, "author": null, "contributor": null}, {"id": "tasks_overhaul_plan_resume_last_conversation", "label": "Resume-last-conversation on launch", "file_type": "rationale", "source_file": "tasks/overhaul-plan.md", "source_location": null, "source_url": null, "captured_at": null, "author": null, "contributor": null}, {"id": "tasks_overhaul_plan_reliability_primitives", "label": "Reliability primitives (retry, keep-partial, offline)", "file_type": "rationale", "source_file": "tasks/overhaul-plan.md", "source_location": null, "source_url": null, "captured_at": null, "author": null, "contributor": null}], "edges": [{"source": "tasks_overhaul_plan_local_first_storage", "target": "hermesvoicekit_conversationstore_conversationstore", "relation": "rationale_for", "confidence": "EXTRACTED", "confidence_score": 1.0, "source_file": "tasks/overhaul-plan.md", "source_location": null, "weight": 1.0}, {"source": "tasks_overhaul_plan_local_first_storage", "target": "hermesvoice_conversationfilestore_conversationfilestore", "relation": "rationale_for", "confidence": "INFERRED", "confidence_score": 0.85, "source_file": "tasks/overhaul-plan.md", "source_location": null, "weight": 1.0}, {"source": "tasks_overhaul_plan_pure_logic_in_kit", "target": "hermesvoicekit_conversationstore_conversationstore", "relation": "rationale_for", "confidence": "EXTRACTED", "confidence_score": 1.0, "source_file": "tasks/overhaul-plan.md", "source_location": null, "weight": 1.0}, {"source": "tasks_overhaul_plan_client_owned_history", "target": "hermesvoice_overlayviewmodel_generateresponse", "relation": "rationale_for", "confidence": "INFERRED", "confidence_score": 0.85, "source_file": "tasks/overhaul-plan.md", "source_location": null, "weight": 1.0}, {"source": "tasks_overhaul_plan_flock_single_instance", "target": "hermesvoice_appdelegate_claimsingleinstancelock", "relation": "rationale_for", "confidence": "EXTRACTED", "confidence_score": 1.0, "source_file": "tasks/overhaul-plan.md", "source_location": null, "weight": 1.0}, {"source": "tasks_overhaul_plan_resume_last_conversation", "target": "hermesvoice_overlayviewmodel_overlayviewmodel", "relation": "rationale_for", "confidence": "INFERRED", "confidence_score": 0.85, "source_file": "tasks/overhaul-plan.md", "source_location": null, "weight": 1.0}, {"source": "tasks_overhaul_plan_reliability_primitives", "target": "hermesvoice_overlayviewmodel_runstream", "relation": "rationale_for", "confidence": "INFERRED", "confidence_score": 0.85, "source_file": "tasks/overhaul-plan.md", "source_location": null, "weight": 1.0}, {"source": "tasks_overhaul_plan_local_first_storage", "target": "tasks_overhaul_plan_client_owned_history", "relation": "conceptually_related_to", "confidence": "INFERRED", "confidence_score": 0.75, "source_file": "tasks/overhaul-plan.md", "source_location": null, "weight": 1.0}], "hyperedges": []}